pyaer/__about__.py
pyaer/__init__.py
pyaer/_libcaer_wrap.cpython-38-x86_64-linux-gnu.so
pyaer/comm.py
pyaer/container.py
pyaer/davis.py
pyaer/device.py
pyaer/dvs128.py
pyaer/dvxplorer.py
pyaer/dynapse.py
pyaer/edvs.py
pyaer/evk.py
pyaer/filters.py
pyaer/libcaer_wrap.py
pyaer/log.py
pyaer/utils.py
pyaer-0.2.6.data/scripts/aer_hub
pyaer-0.2.6.data/scripts/aer_launch
pyaer-0.2.6.data/scripts/aer_lstopic
pyaer-0.2.6.data/scripts/aer_publisher
pyaer-0.2.6.data/scripts/aer_pubsuber
pyaer-0.2.6.data/scripts/aer_saver
pyaer-0.2.6.data/scripts/aer_subscriber
pyaer-0.2.6.dist-info/LICENSE
pyaer-0.2.6.dist-info/METADATA
pyaer-0.2.6.dist-info/WHEEL
pyaer-0.2.6.dist-info/top_level.txt
pyaer-0.2.6.dist-info/RECORD
