Metadata-Version: 2.1
Name: pyaer
Version: 0.2.6
Summary: PyAER: Low-level Python APIs for Accessing Neuromorphic Devices.
Home-page: https://github.com/duguyue100/pyaer
Author: Yuhuang Hu
Author-email: duguyue100@gmail.com
License: UNKNOWN
Platform: UNKNOWN
Classifier: Development Status :: 4 - Beta
Classifier: Intended Audience :: Science/Research
Classifier: Natural Language :: English
Classifier: Operating System :: OS Independent
Classifier: Programming Language :: Python :: 3.6
Classifier: Programming Language :: Python :: 3.7
Classifier: Programming Language :: Python :: 3.8
Classifier: Topic :: Utilities
Classifier: Topic :: Scientific/Engineering
Classifier: Topic :: Scientific/Engineering :: Artificial Intelligence
Classifier: Topic :: Software Development :: Libraries :: Python Modules
Classifier: License :: OSI Approved :: MIT License
Requires-Dist: numpy (>=1.18.0)
